pbs/PBSQuery.py
pbs/__init__.py
pbs/_pbs.cpython-310-x86_64-linux-gnu.so
pbs/_pbs.cpython-38-x86_64-linux-gnu.so
pbs/_pbs.so
pbs/pbs.py
tests/unit/__init__.py
tests/unit/test_pbs_python.py
pbs_python-2024.11.2.post0.dist-info/LICENSE.md
pbs_python-2024.11.2.post0.dist-info/METADATA
pbs_python-2024.11.2.post0.dist-info/WHEEL
pbs_python-2024.11.2.post0.dist-info/top_level.txt
pbs_python-2024.11.2.post0.dist-info/RECORD
