Metadata-Version: 2.1
Name: pbs-python
Version: 2024.11.2.post0
Summary: Utils.
Author-email: "Exabyte Inc." <info@mat3ra.com>
License: # LICENSE
Classifier: Programming Language :: Python
Classifier: Programming Language :: Python :: 3
Classifier: Development Status :: 3 - Alpha
Classifier: Topic :: Software Development
Requires-Python: >=3.8
License-File: LICENSE.md
Provides-Extra: all
Requires-Dist: pbs-python[tests] ; extra == 'all'
Provides-Extra: tests
Requires-Dist: coverage[toml] >=5.3 ; extra == 'tests'
Requires-Dist: pre-commit ; extra == 'tests'
Requires-Dist: black ; extra == 'tests'
Requires-Dist: ruff ; extra == 'tests'
Requires-Dist: isort ; extra == 'tests'
Requires-Dist: mypy ; extra == 'tests'
Requires-Dist: pip-tools ; extra == 'tests'
Requires-Dist: pytest ; extra == 'tests'
Requires-Dist: pytest-cov ; extra == 'tests'
Requires-Dist: pytest-mock ; extra == 'tests'
